.gitignore
LICENSE
flake8_format_ansi.py
setup.cfg
setup.py
flake8_format_ansi.egg-info/PKG-INFO
flake8_format_ansi.egg-info/SOURCES.txt
flake8_format_ansi.egg-info/dependency_links.txt
flake8_format_ansi.egg-info/entry_points.txt
flake8_format_ansi.egg-info/pbr.json
flake8_format_ansi.egg-info/requires.txt
flake8_format_ansi.egg-info/top_level.txt