Metadata-Version: 1.1
Name: flake8-format-ansi
Version: 0.1.0
Summary: ANSI error format plugin for flake8.
Home-page: https://github.com/jayvdb/flake8-format-ansi
Author: John Vandenberg
Author-email: jayvdb@gmail.com
License: MIT License
Keywords: flake8 color ansi error format
Platform: UNKNOWN
Classifier: Development Status :: 3 - Alpha
Classifier: Environment :: Console
Classifier: Intended Audience :: Developers
Classifier: License :: OSI Approved :: MIT License
Classifier: Operating System :: OS Independent
Classifier: Programming Language :: Python
Classifier: Programming Language :: Python :: 2
Classifier: Programming Language :: Python :: 3
Classifier: Topic :: Software Development :: Libraries :: Python Modules
Classifier: Topic :: Software Development :: Quality Assurance
